krakenio/__init__.py
krakenio-0.2.0.dist-info/LICENSE
krakenio-0.2.0.dist-info/METADATA
krakenio-0.2.0.dist-info/WHEEL
krakenio-0.2.0.dist-info/top_level.txt
krakenio-0.2.0.dist-info/RECORD
